README.rst
setup.py
py_xlsx.egg-info/PKG-INFO
py_xlsx.egg-info/SOURCES.txt
py_xlsx.egg-info/dependency_links.txt
py_xlsx.egg-info/top_level.txt
xlsx/__init__.py
xlsx/formatting.py
xlsx/timemachine.py
xlsx/xldate.py